xlsxcursor/__init__.py
Xlsxcursor-0.1.8.dist-info/METADATA
Xlsxcursor-0.1.8.dist-info/WHEEL
Xlsxcursor-0.1.8.dist-info/top_level.txt
Xlsxcursor-0.1.8.dist-info/RECORD
